pygments_gchangelog.py
pygments_gchangelog-0.1.dist-info/RECORD
pygments_gchangelog-0.1.dist-info/WHEEL
pygments_gchangelog-0.1.dist-info/pydist.json
pygments_gchangelog-0.1.dist-info/entry_points.txt
pygments_gchangelog-0.1.dist-info/DESCRIPTION.rst
pygments_gchangelog-0.1.dist-info/top_level.txt
pygments_gchangelog-0.1.dist-info/METADATA
