Metadata-Version: 2.0
Name: pygments-gchangelog
Version: 0.1
Summary: Pygments lexer and style for Gentoo ChangeLog
Home-page: https://github.com/bacher09/pygments-gchangelog
Author: Slava Bacherikov
Author-email: slava@bacherikov.org.ua
License: MIT
Keywords: pygments,lexer,changelog,gentoo
Platform: any
Classifier: Development Status :: 3 - Alpha
Classifier: Operating System :: OS Independent
Classifier: Intended Audience :: Developers
Classifier: License :: OSI Approved :: MIT License
Classifier: Programming Language :: Python
Classifier: Programming Language :: Python :: 2
Classifier: Programming Language :: Python :: 2.6
Classifier: Programming Language :: Python :: 2.7
Classifier: Programming Language :: Python :: 3
Classifier: Programming Language :: Python :: 3.2
Classifier: Programming Language :: Python :: 3.3
Classifier: Topic :: Software Development :: Libraries
Requires-Dist: pygments
